droid_please/__init__.py
droid_please/agent.py
droid_please/agent_tools.py
droid_please/config.py
droid_please/conversations.py
droid_please/llm.py
droid_please/main.py
droid_please/prompts.py
droid_please/util.py
droid_please-0.0.6.dist-info/LICENSE
droid_please-0.0.6.dist-info/METADATA
droid_please-0.0.6.dist-info/WHEEL
droid_please-0.0.6.dist-info/entry_points.txt
droid_please-0.0.6.dist-info/RECORD
